pypyorm/__init__.py
pypyorm/orm.py
pypyorm-0.1.1.dist-info/METADATA
pypyorm-0.1.1.dist-info/RECORD
pypyorm-0.1.1.dist-info/WHEEL
pypyorm-0.1.1.dist-info/top_level.txt
