Metadata-Version: 2.1
Name: pypyorm
Version: 0.1.1
Summary: Easy ORM package
Home-page: https://github.com/dotcoo/pypyorm
Author: dotcoo
Author-email: dotcoo@163.com
License: UNKNOWN
Platform: UNKNOWN
Classifier: Programming Language :: Python :: 3
Classifier: License :: OSI Approved :: MIT License
Classifier: Operating System :: OS Independent
Requires-Dist: pymysql
